ccfraud_detector/__init__.py
ccfraud_detector/detector.py
ccfraud_detector-3.0.0.dist-info/METADATA
ccfraud_detector-3.0.0.dist-info/WHEEL
ccfraud_detector-3.0.0.dist-info/licenses/LICENSE
ccfraud_detector-3.0.0.dist-info/RECORD
