Metadata-Version: 2.4
Name: ccfraud-detector
Version: 3.0.0
Summary: AI-powered credit card fraud detection using Anthropic Claude.
Project-URL: Homepage, https://github.com/AdityaPatange1/creditcard_fraud_classifier
Project-URL: Documentation, https://github.com/AdityaPatange1/creditcard_fraud_classifier#readme
Project-URL: Repository, https://github.com/AdityaPatange1/creditcard_fraud_classifier.git
Project-URL: Issues, https://github.com/AdityaPatange1/creditcard_fraud_classifier/issues
Author-email: Ekta Bhatia <ekta.bhatia@gmail.com>, Aditya Patange <contact.adityapatange@gmail.com>
Maintainer-email: Ekta Bhatia <ekta.bhatia@gmail.com>, Aditya Patange <contact.adityapatange@gmail.com>
License-Expression: MIT
License-File: LICENSE
Keywords: ai,anthropic,claude,credit-card,fintech,fraud-detection,machine-learning,security
Classifier: Development Status :: 5 - Production/Stable
Classifier: Intended Audience :: Developers
Classifier: Intended Audience :: Financial and Insurance Industry
Classifier: License :: OSI Approved :: MIT License
Classifier: Operating System :: OS Independent
Classifier: Programming Language :: Python :: 3
Classifier: Programming Language :: Python :: 3.9
Classifier: Programming Language :: Python :: 3.10
Classifier: Programming Language :: Python :: 3.11
Classifier: Programming Language :: Python :: 3.12
Classifier: Topic :: Office/Business :: Financial
Classifier: Topic :: Security
Requires-Python: >=3.9
Requires-Dist: anthropic>=0.40.0
Requires-Dist: pydantic>=2.0.0
Provides-Extra: dev
Requires-Dist: mypy>=1.13.0; extra == 'dev'
Requires-Dist: pytest-asyncio>=0.24.0; extra == 'dev'
Requires-Dist: pytest>=8.0.0; extra == 'dev'
Requires-Dist: ruff>=0.8.0; extra == 'dev'
